qibocal/__init__.py
qibocal/auto/__init__.py
qibocal/auto/execute.py
qibocal/auto/history.py
qibocal/auto/mode.py
qibocal/auto/operation.py
qibocal/auto/output.py
qibocal/auto/runcard.py
qibocal/auto/serialize.py
qibocal/auto/status.py
qibocal/auto/task.py
qibocal/auto/transpile.py
qibocal/calibration/__init__.py
qibocal/calibration/calibration.py
qibocal/calibration/dummy.json
qibocal/calibration/platform.py
qibocal/calibration/serialize.py
qibocal/cli/__init__.py
qibocal/cli/_base.py
qibocal/cli/acquisition.py
qibocal/cli/compare.py
qibocal/cli/fit.py
qibocal/cli/report.py
qibocal/cli/run.py
qibocal/cli/update.py
qibocal/cli/upload.py
qibocal/config.py
qibocal/fitting/classifier/__init__.py
qibocal/fitting/classifier/data.py
qibocal/fitting/classifier/qblox_fit.py
qibocal/fitting/classifier/qubit_fit.py
qibocal/fitting/classifier/run.py
qibocal/protocols/__init__.py
qibocal/protocols/allxy/__init__.py
qibocal/protocols/allxy/allxy.py
qibocal/protocols/allxy/allxy_resonator_depletion_tuning.py
qibocal/protocols/classification/__init__.py
qibocal/protocols/classification/classification.py
qibocal/protocols/classification/qutrit_classification.py
qibocal/protocols/coherence/__init__.py
qibocal/protocols/coherence/cpmg.py
qibocal/protocols/coherence/spin_echo.py
qibocal/protocols/coherence/spin_echo_signal.py
qibocal/protocols/coherence/t1.py
qibocal/protocols/coherence/t1_flux.py
qibocal/protocols/coherence/t1_signal.py
qibocal/protocols/coherence/t2.py
qibocal/protocols/coherence/t2_flux.py
qibocal/protocols/coherence/t2_signal.py
qibocal/protocols/coherence/utils.py
qibocal/protocols/coherence/zeno.py
qibocal/protocols/dispersive_shift/__init__.py
qibocal/protocols/dispersive_shift/dispersive_shift.py
qibocal/protocols/dispersive_shift/dispersive_shift_qutrit.py
qibocal/protocols/drag/__init__.py
qibocal/protocols/drag/drag.py
qibocal/protocols/drag/drag_simple.py
qibocal/protocols/flipping.py
qibocal/protocols/flux_dependence/__init__.py
qibocal-0.2.4.dist-info/METADATA
qibocal-0.2.4.dist-info/WHEEL
qibocal-0.2.4.dist-info/entry_points.txt
qibocal-0.2.4.dist-info/licenses/LICENSE
qibocal-0.2.4.dist-info/RECORD
