Metadata-Version: 2.4
Name: qibocal
Version: 0.2.4
Summary: Qibo's quantum calibration, characterization and validation module.
License: Apache-2.0
License-File: LICENSE
Author: The Qibo team
Requires-Python: >=3.10,<3.14
Classifier: License :: OSI Approved :: Apache Software License
Classifier: Programming Language :: Python :: 3
Classifier: Programming Language :: Python :: 3.10
Classifier: Programming Language :: Python :: 3.11
Classifier: Programming Language :: Python :: 3.12
Classifier: Programming Language :: Python :: 3.13
Classifier: Topic :: Scientific/Engineering :: Physics
Requires-Dist: click (>=8.1.3,<9.0.0)
Requires-Dist: cma (>=3.3.0,<4.0.0)
Requires-Dist: jinja2 (>=3.1.2,<4.0.0)
Requires-Dist: numpy (>=1.26.4,<3)
Requires-Dist: pandas[html] (>=2.2.2,<3.0.0)
Requires-Dist: plotly (>=5.22.0,<6.0.0)
Requires-Dist: pydantic (>=2.8.0,<3.0.0)
Requires-Dist: qibo (>=0.2.16,<0.3.0)
Requires-Dist: qibolab (>=0.2.8,<0.3.0)
Requires-Dist: scipy (>=1.10.1,<2.0.0)
Requires-Dist: skops (>=0.11,<0.14)
Project-URL: Documentation, https://qibo.science/qibocal/stable/
Project-URL: Homepage, https://qibo.science/
Project-URL: Repository, https://github.com/qiboteam/qibocal/
